fileprep/__init__.py
fileprep-0.0.3.dist-info/LICENSE.txt
fileprep-0.0.3.dist-info/WHEEL
fileprep-0.0.3.dist-info/METADATA
fileprep-0.0.3.dist-info/RECORD
