Metadata-Version: 2.1
Name: fileprep
Version: 0.0.3
Summary: Batch prepare and clean bad formatted excel files for further analysis.
Home-page: https://github.com/v0ku/fileprep
Keywords: data preparation,excel
Author: Christian Schramm
Author-email: cschra@gmail.com
Requires-Python: >=3.7,<4.0
Classifier: Programming Language :: Python :: 3
Classifier: Programming Language :: Python :: 3.7
Classifier: Programming Language :: Python :: 3.8
Requires-Dist: datetime (>=4.3,<5.0)
Requires-Dist: pandas (>=1.0.5,<2.0.0)
Requires-Dist: xlrd (>=1.2.0,<2.0.0)
Project-URL: Repository, https://github.com/v0ku/fileprep
